cogwheels/__init__.py
cogwheels/__version__.py
cogwheels/exceptions/__init__.py
cogwheels/exceptions/deprecations.py
cogwheels/exceptions/settings.py
cogwheels/helpers/__init__.py
cogwheels/helpers/deprecation.py
cogwheels/helpers/settings.py
cogwheels/helpers/utils.py
cogwheels/helpers/tests/__init__.py
cogwheels/helpers/tests/test_deprecation_warning_stacklevel.py
cogwheels/helpers/tests/test_get.py
cogwheels/helpers/tests/test_get_model.py
cogwheels/helpers/tests/test_get_module.py
cogwheels/helpers/tests/test_get_object.py
cogwheels/helpers/tests/test_helper_attribute_shortcuts.py
cogwheels/helpers/tests/test_helper_init.py
cogwheels/helpers/tests/test_invalid_deprecations.py
cogwheels/helpers/tests/test_is_value_from_deprecated_setting.py
cogwheels/tests/__init__.py
cogwheels/tests/base.py
cogwheels/tests/classes.py
cogwheels/tests/models.py
cogwheels/tests/settings.py
cogwheels/tests/urls.py
cogwheels/tests/conf/__init__.py
cogwheels/tests/conf/defaults.py
cogwheels/tests/conf/settings.py
cogwheels/tests/migrations/0001_initial.py
cogwheels/tests/migrations/__init__.py
cogwheels/tests/modules/__init__.py
cogwheels/tests/modules/default_module.py
cogwheels/tests/modules/replacement_module.py
cogwheels/utils/deprecation.py
cogwheels/utils/inspection.py
django_cogwheels-0.3.dist-info/LICENSE
django_cogwheels-0.3.dist-info/METADATA
django_cogwheels-0.3.dist-info/WHEEL
django_cogwheels-0.3.dist-info/top_level.txt
django_cogwheels-0.3.dist-info/RECORD
